{
  "project_info": {
    "project_number": "872713392672",
    "project_id": "bisayaspeak",
    "storage_bucket": "bisayaspeak.firebasestorage.app"
  },
  "client": [
    {
      "client_info": {
        "mobilesdk_app_id": "1:872713392672:android:5ac0764588ded3d5cca245",
        "android_client_info": {
          "package_name": "com.bisayaspeak.ai"
        }
      },
      "oauth_client": [],
      "api_key": [
        {
          "current_key": "AIzaSyDDinM8zddB1GhuUmk1OxaaYg_O7N0vpvY"
        }
      ],
      "services": {
        "appinvite_service": {
          "other_platform_oauth_client": []
        }
      }
    }
  ],
  "configuration_version": "1"
}